MANIFEST.in
README.txt
fmm.py
setup.py
FMM.egg-info/PKG-INFO
FMM.egg-info/SOURCES.txt
FMM.egg-info/dependency_links.txt
FMM.egg-info/top_level.txt
test/test_fmm.py