Metadata-Version: 1.0
Name: FMM
Version: 0.1
Summary: Numerical Computations
Home-page: UNKNOWN
Author: Philip Schleihauf
Author-email: uniphil@gmail.com
License: Public Domain
Platform: UNKNOWN
